zirc/__init__.py
zirc/caps.py
zirc/client.py
zirc/config.py
zirc/connection.py
zirc/errors.py
zirc/event.py
zirc/flood.py
zirc/loop.py
zirc/test.py
zirc/wrappers.py
zirc/ext/__init__.py
zirc/ext/fifo.py
zirc/ext/proxy.py
zirc/ext/sasl.py
zirc/packages/__init__.py
zirc/packages/ConnectionMgr/__init__.py
zirc/packages/ConnectionMgr/connectionmgr/__init__.py
zirc/packages/ConnectionMgr/connectionmgr/manager.py
zirc/resources/events.json
zirc/util/__init__.py
zirc/util/bucket.py
zirc/util/colors.py
zirc/util/repl.py
zirc-1.2.10.dist-info/METADATA
zirc-1.2.10.dist-info/RECORD
zirc-1.2.10.dist-info/WHEEL
zirc-1.2.10.dist-info/top_level.txt
