Metadata-Version: 2.1
Name: zirc
Version: 1.2.10
Summary: Python IRCP Library
Home-page: https://github.com/itslukej/zirc
Author: Luke J.
Author-email: me+zirc@lukej.me
License: GNU
Platform: UNKNOWN
Classifier: Development Status :: 5 - Production/Stable
Classifier: Intended Audience :: Developers
Classifier: License :: OSI Approved :: GNU General Public License v3 (GPLv3)
Classifier: Natural Language :: English
Classifier: Programming Language :: Python
Classifier: Programming Language :: Python :: 2.7
Classifier: Programming Language :: Python :: 3
Classifier: Programming Language :: Python :: 3.2
Classifier: Programming Language :: Python :: 3.3
Classifier: Programming Language :: Python :: 3.4
Classifier: Programming Language :: Python :: 3.5
Classifier: Programming Language :: Python :: 3.6
Classifier: Programming Language :: Python :: Implementation :: CPython
Classifier: Programming Language :: Python :: Implementation :: PyPy
Classifier: Topic :: Communications :: Chat :: Internet Relay Chat
Classifier: Topic :: Software Development :: Libraries :: Python Modules
Requires-Python: >=2.7,!=3.0.*,!=3.1.*
Provides-Extra: pysocks
Requires-Dist: six
Provides-Extra: pysocks
Requires-Dist: pysocks; extra == 'pysocks'
Provides-Extra: pysocks
Requires-Dist: win-inet-pton; (sys_platform=="win32" and python_version == "2.7") and extra == 'pysocks'
